{
  "files": 127329,
  "directories": 22371,
  "totalSize": 1236116727,
  "extensions": {
    "": 3947,
    ".json": 4593,
    ".md": 4603,
    ".sample": 42,
    ".js": 41686,
    ".ttf": 67,
    ".svg": 850,
    ".png": 936,
    ".jsx": 42,
    ".cmd": 208,
    ".ps1": 205,
    ".ts": 31178,
    ".map": 12482,
    ".mjs": 430,
    ".cjs": 3220,
    ".flow": 2224,
    ".yml": 293,
    ".css": 18,
    ".html": 125,
    ".txt": 420,
    ".bnf": 41,
    ".conf": 12,
    ".sh": 91,
    ".gradle": 95,
    ".tpl": 6,
    ".proto": 14,
    ".cts": 2473,
    ".avif": 184,
    ".ico": 4,
    ".jpg": 6,
    ".kts": 32,
    ".toml": 6,
    ".jar": 9,
    ".properties": 47,
    ".bat": 10,
    ".kt": 2394,
    ".java": 2219,
    ".xml": 683,
    ".xcprivacy": 26,
    ".h": 4622,
    ".mm": 1153,
    ".pbxproj": 25,
    ".xcscheme": 10,
    ".podspec": 247,
    ".cpp": 1674,
    ".def": 12,
    ".idl": 27,
    ".config": 14,
    ".props": 17,
    ".vcxproj": 14,
    ".filters": 14,
    ".sln": 24,
    ".tsx": 1184,
    ".lock": 39,
    ".mts": 38,
    ".snap": 3,
    ".applescript": 3,
    ".bplist": 45,
    ".mkd": 9,
    ".markdown": 32,
    ".iml": 4,
    ".yaml": 2,
    ".bsd": 12,
    ".pro": 25,
    ".m": 623,
    ".swift": 785,
    ".rb": 81,
    ".aar": 11,
    ".tsbuildinfo": 3,
    ".md5": 30,
    ".sha1": 30,
    ".pom": 10,
    ".1": 4,
    ".node": 3,
    ".nix": 3,
    ".xyz": 3,
    ".file": 6,
    ".md~": 3,
    ".swf": 3,
    ".hbs": 4,
    ".coffee": 30,
    ".list": 6,
    ".jsdoc": 2,
    ".apache2": 6,
    ".mit": 6,
    ".bin": 126,
    ".strings": 111,
    ".s": 48,
    ".xcconfig": 3,
    ".api": 3,
    ".cmake": 11,
    ".c": 2,
    ".in": 3,
    ".modulemap": 3,
    ".template": 6,
    ".exe": 3,
    ".dll": 27,
    ".plist": 13,
    ".xcworkspacedata": 5,
    ".xcuserstate": 3,
    ".probe": 3,
    ".air": 16,
    ".metallib": 16,
    ".metal": 4,
    ".pegjs": 21,
    ".peg": 9,
    ".rc": 6,
    ".dockerfile": 3,
    ".log": 3,
    ".info": 3,
    ".idx": 1,
    ".pack": 1,
    ".rev": 1,
    ".env": 2,
    ".entitlements": 1,
    ".storyboard": 3,
    ".wav": 2,
    ".command": 1,
    ".bundle": 2,
    ".otf": 18,
    ".jsbundle": 1,
    ".keystore": 1,
    ".wasm": 1,
    ".re": 18,
    ".ml": 2,
    ".opam": 1
  }
}